README.md
setup.py
pybnn/__init__.py
pybnn/base_model.py
pybnn/bayesian_linear_regression.py
pybnn/bohamiann.py
pybnn/dngo.py
pybnn/lcnet.py
pybnn/multi_task_bohamiann.py
pybnn/priors.py
pybnn.egg-info/PKG-INFO
pybnn.egg-info/SOURCES.txt
pybnn.egg-info/dependency_links.txt
pybnn.egg-info/requires.txt
pybnn.egg-info/top_level.txt
pybnn/sampler/__init__.py
pybnn/sampler/adaptive_sghmc.py
pybnn/sampler/old_constant_sgd.py
pybnn/sampler/preconditioned_sgld.py
pybnn/sampler/psgld_hd.py
pybnn/sampler/sghmc.py
pybnn/sampler/sghmc_hd.py
pybnn/sampler/sgld.py
pybnn/util/__init__.py
pybnn/util/infinite_dataloader.py
pybnn/util/layers.py
pybnn/util/normalization.py
test/__init__.py
test/test_bohamiann.py
test/test_dngo.py
test/test_lcnet.py
test/test_mtbohamiann.py
test/test_normalization.py